tap_referral_saasquatch.py
tap_referral_saasquatch-0.1.2.dist-info/DESCRIPTION.rst
tap_referral_saasquatch-0.1.2.dist-info/METADATA
tap_referral_saasquatch-0.1.2.dist-info/RECORD
tap_referral_saasquatch-0.1.2.dist-info/WHEEL
tap_referral_saasquatch-0.1.2.dist-info/entry_points.txt
tap_referral_saasquatch-0.1.2.dist-info/metadata.json
tap_referral_saasquatch-0.1.2.dist-info/top_level.txt
