Metadata-Version: 2.0
Name: tap-referral-saasquatch
Version: 0.1.2
Summary: Taps Referral SaaSquatch data
Home-page: https://github.com/stitchstreams/tap-referral-saasquatch
Author: Stitch
Author-email: UNKNOWN
License: UNKNOWN
Platform: UNKNOWN
Classifier: Programming Language :: Python :: 3 :: Only
Requires-Dist: backoff (==1.3.2)
Requires-Dist: python-dateutil (==2.6.0)
Requires-Dist: requests (==2.12.4)
Requires-Dist: stitchstream-python (>=0.5.0)
